hullencrypt/base.py
hullencrypt/test.py
hullencrypt-0.0.5.dist-info/LICENSE
hullencrypt-0.0.5.dist-info/METADATA
hullencrypt-0.0.5.dist-info/WHEEL
hullencrypt-0.0.5.dist-info/top_level.txt
hullencrypt-0.0.5.dist-info/RECORD
