Metadata-Version: 2.1
Name: hullencrypt
Version: 0.0.5
Summary: A selfmade cryptolib for sharing passwords in a tree structure
Author-email: John Janzen <rc-dev@johnjanzen.me>
Classifier: Programming Language :: Python :: 3
Classifier: License :: OSI Approved :: GNU General Public License (GPL)
Classifier: Operating System :: OS Independent
Requires-Python: >=3.7
License-File: LICENSE
Requires-Dist: cryptography (~=40.0.0)
